db_email/__init__.py
db_email/admin.py
db_email/backend.py
db_email/fields.py
db_email/models.py
db_email/urls.py
db_email/version.py
db_email/views.py
db_email/migrations/0001_initial.py
db_email/migrations/__init__.py
django_db_email-1.0.0.dist-info/METADATA
django_db_email-1.0.0.dist-info/WHEEL
django_db_email-1.0.0.dist-info/top_level.txt
django_db_email-1.0.0.dist-info/RECORD
