Metadata-Version: 2.1
Name: django-db-email
Version: 1.0.0
Summary: Db backend for Django mails
Home-page: https://github.com/bboogaard/django-db-email
Author: Bram Boogaard
Author-email: padawan@hetnet.nl
License: MIT License
Keywords: Django Email Backend
Classifier: Development Status :: 3 - Alpha
Requires-Dist: django ~=4.2.7
